{
    "code": "70000075",
    "url": "https:\/\/info.fda.gov.tw\/MLMS\/H0001D.aspx?Type=Lic&LicId=70000075",
    "time": "2024-02-01 19:41:04",
    "許可證字號": "衛部罕藥輸字第000075號",
    "註銷狀態": "",
    "註銷日期": "",
    "註銷理由": "",
    "製造許可登錄編號": "",
    "有效日期": "120\/11\/30",
    "發證\/登錄日期": "110\/11\/30",
    "許可證\/登錄種類": "製　劑",
    "舊證字號": "",
    "醫療器材級數": "",
    "第一等級醫療器材原許可證字號": "",
    "第一等級醫療器材新登錄字號": "",
    "通關簽審文件編號": "DHA07000007506",
    "中文品名": "服脊立口服溶液用粉劑0.75毫克\/毫升",
    "英文品名": "EVRYSDI Powder for Oral Solution 0.75 mg\/mL",
    "適應症": "適用於治療經基因確診且已出現症狀之脊髓性肌肉萎縮症(SMA)第一、二、三型病人，但不適用於已使用呼吸器每天十二小時以上且連續超過三十天者。",
    "劑型": "14C口服溶液用粉劑",
    "包裝": "(附瓶身轉接器與口服餵藥器組)2-1000公克玻璃瓶裝",
    "儲存溫度": "",
    "有效期間": "",
    "指示藥品審查基準": "",
    "標籤、仿單及包裝加註": "",
    "藥品類別": "06須由醫師處方使用",
    "管制藥品分類級別": "",
    "藥品分類": "新成分;",
    "監視期限": "115\/11\/30",
    "主成分略述": "risdiplam",
    "限制項目": "02輸　入",
    "申請商名稱": "羅氏大藥廠股份有限公司",
    "申請商地址": "台北市信義區松仁路100號40樓、40樓之1、41樓之1",
    "主製造廠": [
        {
            "製造廠名稱": "F. HOFFMANN-LA ROCHE LTD.",
            "製造廠廠址": "GRENZACHERSTRASSE 124, CH-4070 BASEL, SWITZERLAND",
            "製造廠公司地址": "",
            "製造廠國別": "SWITZERLAND",
            "製程": ""
        }
    ],
    "次製造廠": [
        {
            "製造廠名稱": "裕利股份有限公司",
            "製造廠廠址": "桃園市大園區和平里1鄰開和路91號",
            "製造廠公司地址": "",
            "製造廠國別": "TAIWAN",
            "製程": "二級包裝廠(委託貼標及置入仿單)"
        },
        {
            "製造廠名稱": "F. HOFFMANN-LA ROCHE LTD.",
            "製造廠廠址": "WURMISWEG, CH-4303 KAISERAUGST, SWITZERLAND",
            "製造廠公司地址": "",
            "製造廠國別": "SWITZERLAND",
            "製程": "包裝"
        }
    ],
    "CCC號列": "",
    "藥理治療分類": "",
    "ingredients": [
        {
            "成分類別": "主成分",
            "成分代碼": "5236004000",
            "成分名稱": "risdiplam",
            "含量描述": "",
            "含量": "60.0000000000",
            "單位": "MG"
        }
    ],
    "仿單外盒": [
        {
            "title": "EVRYSDI 中文標籤-110-12-16.pdf",
            "url": "https:\/\/www.fda.gov.tw\/MLMS\/ShowFile.aspx?LicId=70000075&Seq=003&Type=8"
        },
        {
            "title": "7. Evrysdi 服脊立_瓶標_10227860-110-12-16.pdf",
            "url": "https:\/\/www.fda.gov.tw\/MLMS\/ShowFile.aspx?LicId=70000075&Seq=002&Type=8"
        },
        {
            "title": "6. Evrysdi 服脊立_外盒_10227859-110-12-16.pdf",
            "url": "https:\/\/www.fda.gov.tw\/MLMS\/ShowFile.aspx?LicId=70000075&Seq=001&Type=8"
        }
    ]
}