{
    "code": "94017340",
    "url": "https:\/\/info.fda.gov.tw\/MLMS\/H0001D.aspx?Type=Lic&LicId=94017340",
    "time": "2020-02-26 12:07:01",
    "許可證字號": "衛部醫器輸壹字第017340號",
    "註銷狀態": "",
    "註銷日期": "",
    "註銷理由": "",
    "製造許可登錄編號": "",
    "有效日期": "110\/12\/26",
    "發證日期": "105\/12\/26",
    "許可證種類": "醫　器",
    "舊證字號": "",
    "醫療器材級數": "第一等級",
    "通關簽審文件編號": "DHA09401734002",
    "中文品名": "&quot;悅廷和&quot; 超音波清洗機 (未滅菌)",
    "英文品名": "&quot;Getinge&quot; Ultrasonic Cleaner (Non-Sterile)",
    "效能": "限醫療器材管理辦法「醫療器械用超音波洗淨機(J.6150)」第一等級鑑別範圍。",
    "醫器規格": "空白。",
    "劑型": "",
    "包裝": "",
    "儲存溫度": "",
    "有效期間": "",
    "指示藥品審查基準": "",
    "標籤、仿單及包裝加註": "",
    "醫器主類別一": "J一般醫院及個人使用裝置",
    "醫器次類別一": "J6150醫療器械用超音波洗淨機",
    "醫器主類別二": "",
    "醫器次類別二": "",
    "醫器主類別三": "",
    "醫器次類別三": "",
    "藥品分類": "",
    "監視期限": "",
    "主成分略述": "",
    "限制項目": "02輸　入",
    "申請商名稱": "620117L464  台灣悅廷和有限公司",
    "申請商地址": "臺北市信義區市民大道6段288號6樓之8",
    "主製造廠": [
        {
            "製造廠名稱": "MSE0831000  GETINGE INFECTION CONTROL AB",
            "製造廠廠址": "P.O BOX 69 SE-305 05 GETINGE SWEDEN",
            "製造廠公司地址": "",
            "製造廠國別": "SWEDEN",
            "製程": ""
        }
    ],
    "藥理治療分類": "",
    "ingredients": []
}