{
    "code": "03015271",
    "url": "https:\/\/info.fda.gov.tw\/MLMS\/H0001D.aspx?Type=Lic&LicId=03015271",
    "time": "2024-02-29 21:45:42",
    "許可證字號": "衛署成製字第015271號",
    "註銷狀態": "",
    "註銷日期": "",
    "註銷理由": "",
    "製造許可登錄編號": "",
    "有效日期": "113\/04\/17",
    "發證\/登錄日期": "98\/04\/17",
    "許可證\/登錄種類": "製　劑",
    "舊證字號": "",
    "醫療器材級數": "",
    "第一等級醫療器材原許可證字號": "",
    "第一等級醫療器材新登錄字號": "",
    "通關簽審文件編號": "DHY00301527102",
    "中文品名": "一必通浣腸液",
    "英文品名": "Yi Bi Tong Enema",
    "適應症": "緩解便祕。",
    "劑型": "501浣腸劑",
    "包裝": "2~25粒(每粒20毫升)塑膠球裝",
    "儲存溫度": "",
    "有效期間": "",
    "指示藥品審查基準": "",
    "標籤、仿單及包裝加註": "",
    "藥品類別": "03成藥",
    "管制藥品分類級別": "",
    "藥品分類": "",
    "監視期限": "",
    "主成分略述": "SODIUM CHLORIDE, GLYCERIN (eq to GLYCEROL)",
    "限制項目": "01國　產",
    "申請商名稱": "久仁製藥廠股份有限公司",
    "申請商地址": "南投縣南投市永豐里工業路５９號",
    "主製造廠": [
        {
            "製造廠名稱": "久仁製藥廠股份有限公司",
            "製造廠廠址": "南投縣南投市永豐里工業路５９號",
            "製造廠公司地址": "",
            "製造廠國別": "TAIWAN",
            "製程": ""
        }
    ],
    "CCC號列": "",
    "藥理治療分類": "",
    "ingredients": [
        {
            "成分類別": "主成分",
            "成分代碼": "4012002100",
            "成分名稱": "SODIUM CHLORIDE",
            "含量描述": "",
            "含量": "150.0000000000",
            "單位": "MG"
        },
        {
            "成分類別": "主成分",
            "成分代碼": "9600013500",
            "成分名稱": "GLYCERIN (eq to GLYCEROL)",
            "含量描述": "",
            "含量": "300.0000000000",
            "單位": "MG"
        }
    ],
    "藥物辨識詳細資料": {
        "外觀尺寸": "",
        "特殊劑型": "",
        "顏色": "",
        "特殊氣味": "",
        "刻痕": "",
        "形狀": "",
        "標記一": "",
        "標記二": ""
    },
    "藥物辨識外觀圖片": [
        {
            "title": "一必通浣腸液-110-12-17(廠商自行上傳).pdf",
            "url": "https:\/\/www.fda.gov.tw\/MLMS\/ShowFile.aspx?LicId=03015271&Seq=003&Type=10"
        },
        {
            "title": "011-104-09-16(廠商自行上傳).PDF",
            "url": "https:\/\/www.fda.gov.tw\/MLMS\/ShowFile.aspx?LicId=03015271&Seq=002&Type=10"
        }
    ],
    "仿單外盒": [
        {
            "title": "一必通浣腸液說明書-110-12-14(廠商自行上傳).pdf",
            "url": "https:\/\/www.fda.gov.tw\/MLMS\/ShowFile.aspx?LicId=03015271&Seq=005&Type=9"
        },
        {
            "title": "015271塑膠-108-12-09.pdf",
            "url": "https:\/\/www.fda.gov.tw\/MLMS\/ShowFile.aspx?LicId=03015271&Seq=004&Type=9"
        },
        {
            "title": "015271仿單-108-12-09.pdf",
            "url": "https:\/\/www.fda.gov.tw\/MLMS\/ShowFile.aspx?LicId=03015271&Seq=003&Type=9"
        },
        {
            "title": "一必通- 青年生技-110-12-23(廠商自行上傳).pdf",
            "url": "https:\/\/www.fda.gov.tw\/MLMS\/ShowFile.aspx?LicId=03015271&Seq=008&Type=8"
        },
        {
            "title": "015271-108-12-09.pdf",
            "url": "https:\/\/www.fda.gov.tw\/MLMS\/ShowFile.aspx?LicId=03015271&Seq=006&Type=8"
        }
    ]
}