{
    "code": "05003678",
    "url": "https:\/\/info.fda.gov.tw\/MLMS\/H0001D.aspx?Type=Lic&LicId=05003678",
    "time": "2022-10-14 07:03:45",
    "許可證字號": "衛署醫器製字第003678號",
    "註銷狀態": "已註銷",
    "註銷日期": "111\/01\/24",
    "註銷理由": "自請註銷",
    "製造許可登錄編號": "GMP1040",
    "有效日期": "111\/08\/02",
    "發證日期": "101\/08\/16",
    "許可證種類": "醫　器",
    "舊證字號": "",
    "醫療器材級數": "第二等級",
    "第一等級醫療器材原登錄字號": "",
    "第一等級醫療器材新登錄字號": "",
    "通關簽審文件編號": "",
    "中文品名": "歐克密葡萄糖試驗系統",
    "英文品名": "OKme Glucose Test System",
    "效能": "適用體外診斷，用於量測新鮮指尖微血管血液的葡萄糖濃度。",
    "醫器規格": "1.歐克密葡萄糖試驗系統：歐克密血糖儀, 歐克密血糖測試片*25, 歐克密葡萄糖品管液, 採血筆針*25。 2.歐克密血糖測試片：試片*50, 採血針*50。3.歐克密血糖測試片：試片*50,以下空白",
    "劑型": "",
    "包裝": "",
    "儲存溫度": "",
    "有效期間": "",
    "指示藥品審查基準": "",
    "標籤、仿單及包裝加註": "",
    "醫器主類別一": "A臨床化學及臨床毒理學",
    "醫器次類別一": "A1345葡萄糖試驗系統",
    "醫器主類別二": "",
    "醫器次類別二": "",
    "醫器主類別三": "",
    "醫器次類別三": "",
    "藥品分類": "",
    "監視期限": "",
    "主成分略述": "",
    "限制項目": "01國　產 09委託製造",
    "申請商名稱": "621201A561  康揚國際有限公司",
    "申請商地址": "新竹市東區埔頂里公道五路二段85號",
    "主製造廠": [
        {
            "製造廠名稱": "6112011379  訊映光電股份有限公司",
            "製造廠廠址": "新竹市東區埔頂里公道五路2段91號、91號2-6樓",
            "製造廠公司地址": "",
            "製造廠國別": "TAIWAN",
            "製程": ""
        }
    ],
    "藥理治療分類": "",
    "ingredients": [],
    "仿單外盒": [
        {
            "title": "050036780001___20121122.pdf",
            "url": "https:\/\/www.fda.gov.tw\/MLMS\/ShowFile.aspx?LicId=05003678&Seq=001&Type=9"
        },
        {
            "title": "05003678___20121122.pdf",
            "url": "https:\/\/www.fda.gov.tw\/MLMS\/ShowFile.aspx?LicId=05003678&Seq=002&Type=8"
        },
        {
            "title": "050036780002___20121122.pdf",
            "url": "https:\/\/www.fda.gov.tw\/MLMS\/ShowFile.aspx?LicId=05003678&Seq=001&Type=8"
        }
    ]
}