{
    "code": "01052544",
    "許可證字號": "衛署藥製字第052544號",
    "註銷狀態": "",
    "註銷日期": "",
    "註銷理由": "",
    "有效日期": "109\/03\/09",
    "發證日期": "99\/03\/09",
    "許可證種類": "製　劑",
    "舊證字號": "",
    "醫療器材級數": "",
    "通關簽審文件編號": "DHY00105254404",
    "中文品名": "“信東”0.298%氯化鉀注射液",
    "英文品名": "0.298% KCl in 0.9% NaCl Injection“TBC”",
    "適應症": "治療鉀缺乏症。",
    "劑型": "279注射液",
    "包裝": "500毫升塑膠瓶裝 500毫升軟袋裝",
    "藥品類別": "05限由醫師使用",
    "管制藥品分類級別": "",
    "主成分略述": "POTASSIUM CHLORIDE",
    "限制項目": [
        "01國產"
    ],
    "申請商名稱": "6132010010  信東生技股份有限公司",
    "申請商地址": "桃園市桃園區介壽路22號",
    "主製造廠": {
        "製造廠名稱": "6132010010  信東生技股份有限公司",
        "製造廠廠址": "桃園市桃園區介壽路22號",
        "製造廠公司地址": "",
        "製造廠國別": "TAIWAN",
        "製程": ""
    },
    "CCC號列": "",
    "藥理治療分類": "",
    "ingredients": [
        {
            "成分類別": "主成分",
            "成分代碼": "4012001800",
            "成分名稱": "POTASSIUM CHLORIDE",
            "含量描述": "",
            "含量": "2.9800000000",
            "單位": "MG"
        }
    ],
    "仿單外盒": [
        {
            "title": "仿單 04 0.298% KCl in 0.9% NaCl Injection (衛署藥製字第052544號 G-10896)-20140403再修改-103-06-11.pdf 010525440001___20110705.jpg",
            "url": "http:\/\/www.fda.gov.tw\/MLMS\/(S(knoy1cz5iwyfatvvguaez0re))\/ShowFile.aspx?LicId=01052544&Seq=002&Type=9"
        },
        {
            "title": "外盒 010525440004___20110705.jpg 010525440003___20110705.jpg 010525440002___20110705.jpg",
            "url": "http:\/\/www.fda.gov.tw\/MLMS\/(S(knoy1cz5iwyfatvvguaez0re))\/ShowFile.aspx?LicId=01052544&Seq=003&Type=8"
        }
    ]
}