{
    "code": "01050170",
    "url": "http:\/\/www.fda.gov.tw\/MLMS\/H0001D.aspx?Type=Lic&LicId=01050170",
    "time": "2016-09-30 03:37:16",
    "許可證字號": "衛署藥製字第050170號",
    "註銷狀態": "",
    "註銷日期": "",
    "註銷理由": "",
    "有效日期": "108\/06\/05",
    "發證日期": "98\/06\/05",
    "許可證種類": "製　劑",
    "舊證字號": "",
    "醫療器材級數": "",
    "通關簽審文件編號": "DHY00105017005",
    "中文品名": "“派頓”膚皮樂乳膏 0.25%",
    "英文品名": "Desone Cream 0.25%“Patron”",
    "適應症": "濕疹、牛皮癬、燒傷、曬傷、昆蟲咬傷等皮膚感染症。",
    "劑型": "363乳膏劑",
    "包裝": "1000公克以下鋁軟管",
    "藥品類別": "06須由醫師處方使用",
    "管制藥品分類級別": "",
    "主成分略述": "DESOXIMETASONE",
    "限制項目": [
        "01國產"
    ],
    "申請商名稱": "1427122200  臺灣派頓化學製藥股份有限公司",
    "申請商地址": "高雄市岡山區為隨東路50號",
    "主製造廠": {
        "製造廠名稱": "1427122200  臺灣派頓化學製藥股份有限公司",
        "製造廠廠址": "高雄市岡山區為隨東路50號",
        "製造廠公司地址": "",
        "製造廠國別": "TAIWAN",
        "製程": ""
    },
    "CCC號列": "30043200002 含有腎上腺皮質類固醇荷爾蒙，其衍生物及結構式類似者Containing adrenal corticosteroid hormones, their derivatives and structural analogues",
    "藥理治療分類": "",
    "ingredients": [
        {
            "成分類別": "主成分",
            "成分代碼": "6804002100",
            "成分名稱": "DESOXIMETASONE",
            "含量描述": "",
            "含量": "2.5000000000",
            "單位": "MG"
        }
    ],
    "仿單外盒": [
        {
            "title": "010501700001-104-12-18(廠商自行上傳).pdf",
            "url": "http:\/\/www.fda.gov.tw\/MLMS\/ShowFile.aspx?LicId=01050170&Seq=001&Type=9"
        },
        {
            "title": "010501700002彩盒-104-12-31(廠商自行上傳).pdf",
            "url": "http:\/\/www.fda.gov.tw\/MLMS\/ShowFile.aspx?LicId=01050170&Seq=001&Type=8"
        }
    ]
}