{
    "code": "02004428",
    "url": "http:\/\/www.fda.gov.tw\/MLMS\/H0001D.aspx?Type=Lic&LicId=02004428",
    "time": "2015-08-23 03:50:07",
    "許可證字號": "衛署藥輸字第004428號",
    "註銷狀態": "已註銷",
    "註銷日期": "76\/03\/24",
    "註銷理由": "有效期間已屆未能補件",
    "有效日期": "74\/07\/13",
    "發證日期": "65\/07\/13",
    "許可證種類": "製　劑",
    "舊證字號": "",
    "醫療器材級數": "",
    "通關簽審文件編號": "DHA00200442802",
    "中文品名": "蒙諾安敏注射液",
    "英文品名": "AMINOACIN L300",
    "適應症": "體內蛋白質缺乏症、燒傷、急性發熱及中毒現象、惡病體質、懷孕期嘔吐",
    "劑型": "270注射劑",
    "包裝": "瓶裝",
    "藥品類別": "05限由醫師使用",
    "管制藥品分類級別": "",
    "主成分略述": "XYLITOL, L-ALANINE, ARGININE HCL L-, ASPARTIC ACID DL-, HISTIDINE L- HCL MONOHYDRATE, L-ISOLEUCINE, L-LEUCINE, LYSINE L- HCL ( EQ TO L-LYSINE HCL), L-METHIONINE, L-PHENYLALANINE, L-PROLINE, L-THREONINE, L-TRYPTOPHAN, L-VALINE, GLYCINE (EQ TO AMINOACETIC ACID)(EQ TO GLYCOCOLL), ACETATE, CHLORIDE ION, MAGNESIUM ION, POTASSIUM ION, SODIUM ION, NIACINAMIDE (NICOTINAMIDE), RIBOFLAVIN (VIT B2), PYRIDOXINE HCL, INOSITOL (MESO-INOSITOL), MALIC ACID L-",
    "限制項目": [
        "02輸入"
    ],
    "申請商名稱": "0408621100  公盟企業有限公司",
    "申請商地址": "高雄巿新興區漢民里新興路６８號",
    "主製造廠": {
        "製造廠名稱": "F470170000  SCHIWA GMBH",
        "製造廠廠址": "P.O.B0X 1180 4519GLANDROFF",
        "製造廠公司地址": "",
        "製造廠國別": "GERMANY",
        "製程": ""
    },
    "CCC號列": "",
    "藥理治療分類": "",
    "ingredients": [
        {
            "成分類別": "主成分",
            "成分代碼": "4020001900",
            "成分名稱": "XYLITOL",
            "含量描述": "50",
            "含量": "50.0000000000",
            "單位": "GM"
        },
        {
            "成分類別": "主成分",
            "成分代碼": "4020100202",
            "成分名稱": "L-ALANINE",
            "含量描述": "6.0",
            "含量": "6.0000000000",
            "單位": "GM"
        },
        {
            "成分類別": "主成分",
            "成分代碼": "4020100312",
            "成分名稱": "ARGININE HCL L-",
            "含量描述": "3.0",
            "含量": "3.0000000000",
            "單位": "GM"
        },
        {
            "成分類別": "主成分",
            "成分代碼": "4020100403",
            "成分名稱": "ASPARTIC ACID DL-",
            "含量描述": "0.5",
            "含量": "0.5000000000",
            "單位": "GM"
        },
        {
            "成分類別": "主成分",
            "成分代碼": "4020100922",
            "成分名稱": "HISTIDINE L- HCL MONOHYDRATE",
            "含量描述": "0.8",
            "含量": "0.8000000000",
            "單位": "GM"
        },
        {
            "成分類別": "主成分",
            "成分代碼": "4020101002",
            "成分名稱": "L-ISOLEUCINE",
            "含量描述": "0.7",
            "含量": "0.7000000000",
            "單位": "GM"
        },
        {
            "成分類別": "主成分",
            "成分代碼": "4020101202",
            "成分名稱": "L-LEUCINE",
            "含量描述": "1.1",
            "含量": "1.1000000000",
            "單位": "GM"
        },
        {
            "成分類別": "主成分",
            "成分代碼": "4020101312",
            "成分名稱": "LYSINE L- HCL ( EQ TO L-LYSINE HCL)",
            "含量描述": "1.1",
            "含量": "1.1000000000",
            "單位": "GM"
        },
        {
            "成分類別": "主成分",
            "成分代碼": "4020101502",
            "成分名稱": "L-METHIONINE",
            "含量描述": "1.1",
            "含量": "1.1000000000",
            "單位": "GM"
        },
        {
            "成分類別": "主成分",
            "成分代碼": "4020101702",
            "成分名稱": "L-PHENYLALANINE",
            "含量描述": "1.1",
            "含量": "1.1000000000",
            "單位": "GM"
        },
        {
            "成分類別": "主成分",
            "成分代碼": "4020101802",
            "成分名稱": "L-PROLINE",
            "含量描述": "1.5",
            "含量": "1.5000000000",
            "單位": "GM"
        },
        {
            "成分類別": "主成分",
            "成分代碼": "4020102002",
            "成分名稱": "L-THREONINE",
            "含量描述": "0.5",
            "含量": "0.5000000000",
            "單位": "GM"
        },
        {
            "成分類別": "主成分",
            "成分代碼": "4020102102",
            "成分名稱": "L-TRYPTOPHAN",
            "含量描述": "0.3",
            "含量": "0.3000000000",
            "單位": "GM"
        },
        {
            "成分類別": "主成分",
            "成分代碼": "4020102302",
            "成分名稱": "L-VALINE",
            "含量描述": "0.8",
            "含量": "0.8000000000",
            "單位": "GM"
        },
        {
            "成分類別": "主成分",
            "成分代碼": "4020102400",
            "成分名稱": "GLYCINE (EQ TO AMINOACETIC ACID)(EQ TO GLYCOCOLL)",
            "含量描述": "7.5",
            "含量": "7.5000000000",
            "單位": "GM"
        },
        {
            "成分類別": "主成分",
            "成分代碼": "4026000100",
            "成分名稱": "ACETATE",
            "含量描述": "(35.3MEQ) 2.083",
            "含量": "",
            "單位": "GM"
        },
        {
            "成分類別": "主成分",
            "成分代碼": "4026000510",
            "成分名稱": "CHLORIDE ION",
            "含量描述": "(53.3MEQ) 1.889",
            "含量": "",
            "單位": "GM"
        },
        {
            "成分類別": "主成分",
            "成分代碼": "4026001110",
            "成分名稱": "MAGNESIUM ION",
            "含量描述": "(4.9MEQ) 0.060",
            "含量": "",
            "單位": "GM"
        },
        {
            "成分類別": "主成分",
            "成分代碼": "4026001510",
            "成分名稱": "POTASSIUM ION",
            "含量描述": "(24.1MEQ) 0.945",
            "含量": "",
            "單位": "GM"
        },
        {
            "成分類別": "主成分",
            "成分代碼": "4026001710",
            "成分名稱": "SODIUM ION",
            "含量描述": "(35.3MEQ) 0.811",
            "含量": "",
            "單位": "GM"
        },
        {
            "成分類別": "主成分",
            "成分代碼": "8810000300",
            "成分名稱": "NIACINAMIDE (NICOTINAMIDE)",
            "含量描述": "0.1",
            "含量": "0.1000000000",
            "單位": "GM"
        },
        {
            "成分類別": "主成分",
            "成分代碼": "8810200400",
            "成分名稱": "RIBOFLAVIN (VIT B2)",
            "含量描述": "4",
            "含量": "4.0000000000",
            "單位": "MG"
        },
        {
            "成分類別": "主成分",
            "成分代碼": "8810600300",
            "成分名稱": "PYRIDOXINE HCL",
            "含量描述": "30",
            "含量": "30.0000000000",
            "單位": "MG"
        },
        {
            "成分類別": "主成分",
            "成分代碼": "8813000100",
            "成分名稱": "INOSITOL (MESO-INOSITOL)",
            "含量描述": "0.5",
            "含量": "0.5000000000",
            "單位": "GM"
        },
        {
            "成分類別": "主成分",
            "成分代碼": "9600017802",
            "成分名稱": "MALIC ACID L-",
            "含量描述": "3.0",
            "含量": "3.0000000000",
            "單位": "GM"
        }
    ]
}