{
    "code": "02006974",
    "url": "https:\/\/www.fda.gov.tw\/MLMS\/H0001D.aspx?Type=Lic&LicId=02006974",
    "time": "2020-02-25 08:54:33",
    "許可證字號": "衛署藥輸字第006974號",
    "註銷狀態": "已註銷",
    "註銷日期": "99\/08\/16",
    "註銷理由": "屆期未申請展延",
    "有效日期": "92\/03\/07",
    "發證日期": "69\/03\/07",
    "許可證種類": "製　劑",
    "舊證字號": "",
    "醫療器材級數": "",
    "通關簽審文件編號": "DHA00200697400",
    "中文品名": "達克寧靜脈注射液",
    "英文品名": "DAKTARIN I.V.",
    "適應症": "由念珠菌、麴菌屬、腦膜炎囊球菌等所引起之全身性黴菌感染症",
    "劑型": "270注射劑",
    "包裝": "安瓿",
    "儲存溫度": "",
    "有效期間": "",
    "指示藥品審查基準": "",
    "標籤、仿單及包裝加註": [
        ""
    ],
    "藥品類別": "05限由醫師使用",
    "藥品分類": "",
    "主製造廠": {
        "限制項目": "02輸　入",
        "申請商名稱": "1507401100  嬌生股份有限公司",
        "申請商地址": "台北巿敦化南路２段３１９號３、４、５樓",
        "主製造廠": ""
    },
    "CCC號列": "30042000211 人用醫藥製劑，含抗黴菌劑類抗生素者Medicaments, containing antifungal antibiotics, for human use",
    "藥理治療分類": "",
    "ingredients": [
        {
            "成分類別": "主成分",
            "成分代碼": "0812200800",
            "成分名稱": "MICONAZOLE",
            "含量描述": "10",
            "含量": "10.0000000000",
            "單位": "MG"
        }
    ]
}