{
    "code": "02011389",
    "url": "https:\/\/info.fda.gov.tw\/MLMS\/H0001D.aspx?Type=Lic&LicId=02011389",
    "time": "2020-02-25 09:53:53",
    "許可證字號": "衛署藥輸字第011389號",
    "註銷狀態": "已註銷",
    "註銷日期": "82\/12\/10",
    "註銷理由": "未參加評估（一）",
    "製造許可登錄編號": "",
    "有效日期": "82\/01\/09",
    "發證日期": "72\/06\/08",
    "許可證種類": "製　劑",
    "舊證字號": "02003997",
    "醫療器材級數": "",
    "通關簽審文件編號": "DHA00201138906",
    "中文品名": "疾落錠１００公絲",
    "英文品名": "PECTITE TABLETS 100MG",
    "適應症": "下列各種症狀之袪痰：急、慢性支氣管炎、支氣管擴張症、支氣管氣喘、喉頭炎",
    "劑型": "116膜衣錠",
    "包裝": "瓶裝",
    "儲存溫度": "",
    "有效期間": "",
    "指示藥品審查基準": "",
    "標籤、仿單及包裝加註": "",
    "藥品類別": "06須由醫師處方使用",
    "管制藥品分類級別": "",
    "藥品分類": "",
    "監視期限": "",
    "主成分略述": "MECYSTEINE HCL (CYSTEINE L- METHYLESTER HCL)",
    "限制項目": "02輸　入",
    "申請商名稱": "0605801100  光生行股份有限公司",
    "申請商地址": "台北巿羅斯福路一段１１９巷１６號",
    "主製造廠": [
        {
            "製造廠名稱": "FJP0131000  KISSEI PHARMACEUTICAL CO. LTD.",
            "製造廠廠址": "19-48, YOSHINO, MATSUMOTO CITY NAGANO-PREFECTURE.",
            "製造廠公司地址": "",
            "製造廠國別": "JAPAN",
            "製程": ""
        }
    ],
    "CCC號列": "",
    "藥理治療分類": "",
    "ingredients": [
        {
            "成分類別": "主成分",
            "成分代碼": "4800002210",
            "成分名稱": "MECYSTEINE HCL (CYSTEINE L- METHYLESTER HCL)",
            "含量描述": "100.0",
            "含量": "100.0000000000",
            "單位": "MG"
        }
    ]
}