{
    "code": "02015760",
    "url": "http:\/\/www.fda.gov.tw\/MLMS\/H0001D.aspx?Type=Lic&LicId=02015760",
    "time": "2016-11-18 19:01:40",
    "許可證字號": "衛署藥輸字第015760號",
    "註銷狀態": "已註銷",
    "註銷日期": "105\/05\/18",
    "註銷理由": "未展延而逾期者",
    "有效日期": "93\/03\/19",
    "發證日期": "76\/03\/19",
    "許可證種類": "原料藥",
    "舊證字號": "",
    "醫療器材級數": "",
    "通關簽審文件編號": "DHA00201576005",
    "中文品名": "芬諾普芬鈣（膠囊用）",
    "英文品名": "FENOPROFEN CALCIUM FOR PULVULES",
    "適應症": "鎮痛、抗炎劑",
    "劑型": "040（粉）",
    "包裝": "０．５公斤以上",
    "標籤、仿單及包裝加註": "",
    "藥品類別": "02自用製劑原料",
    "主成分略述": [
        "FENOPROFENCALCIUM"
    ],
    "限制項目": "02輸　入",
    "申請商名稱": "1411306300  臺灣禮來股份有限公司新竹廠",
    "主製造廠": {
        "主製造廠": "",
        "製造廠名稱": "F460073000  ELI. LILLY &amp; CO.",
        "製造廠廠址": "INDIANAPOLIS INDIANA 46285",
        "製造廠公司地址": "",
        "": ""
    },
    "CCC號列": "",
    "藥理治療分類": "",
    "ingredients": [
        {
            "成分類別": "主成分",
            "成分代碼": "2808400710",
            "成分名稱": "FENOPROFEN CALCIUM",
            "含量描述": "97.0-103.0",
            "含量": "",
            "單位": "%"
        }
    ]
}