{
    "code": "02010952",
    "url": "http:\/\/www.fda.gov.tw\/MLMS\/H0001D.aspx?Type=Lic&LicId=02010952",
    "time": "2015-08-23 07:29:20",
    "許可證字號": "衛署藥輸字第010952號",
    "註銷狀態": "已註銷",
    "註銷日期": "89\/10\/18",
    "註銷理由": "未展延而逾期者",
    "有效日期": "81\/03\/07",
    "發證日期": "72\/03\/07",
    "許可證種類": "製　劑",
    "舊證字號": "",
    "醫療器材級數": "",
    "通關簽審文件編號": "DHA00201095202",
    "中文品名": "止血寧錠",
    "英文品名": "TRANEXAMIC ACID TABLETS \"OHTA\"",
    "適應症": "全身及局部出血或出血性疾病",
    "劑型": "110錠劑",
    "包裝": "盒裝",
    "藥品類別": "06須由醫師處方使用",
    "管制藥品分類級別": "",
    "主成分略述": "TRANEXAMIC ACID",
    "限制項目": [
        "02輸入"
    ],
    "申請商名稱": "0913201100  茂元企業有限公司",
    "申請商地址": "台北巿民生東路四段１１２巷３弄１７號",
    "主製造廠": {
        "製造廠名稱": "F260240000  OHTA PHARMACEUTICAL CO. LTD.",
        "製造廠廠址": "51 SANJO-MACHI, SAITAMA-SHI,SAITAMA,JAPAN",
        "製造廠公司地址": "",
        "製造廠國別": "JAPAN",
        "製程": ""
    },
    "CCC號列": "",
    "藥理治療分類": "",
    "ingredients": [
        {
            "成分類別": "主成分",
            "成分代碼": "2012101300",
            "成分名稱": "TRANEXAMIC ACID",
            "含量描述": "250",
            "含量": "250.0000000000",
            "單位": "MG"
        }
    ]
}