{
    "code": "02022823",
    "url": "http:\/\/www.fda.gov.tw\/MLMS\/H0001D.aspx?Type=Lic&LicId=02022823",
    "time": "2017-05-19 03:04:27",
    "許可證字號": "衛署藥輸字第022823號",
    "註銷狀態": "",
    "註銷日期": "",
    "註銷理由": "",
    "有效日期": "109\/04\/07",
    "發證日期": "89\/04\/07",
    "許可證種類": "製　劑",
    "舊證字號": "",
    "醫療器材級數": "",
    "通關簽審文件編號": "DHA00202282307",
    "中文品名": "鎮頑癲膠囊１００毫克",
    "英文品名": "NEURONTIN CAPSULES 100MG",
    "適應症": "治療成人及三歲以上兒童局部癲癇發作之輔助療法。帶狀庖疹後神經痛。",
    "劑型": "130膠囊劑",
    "包裝": "塑膠瓶裝",
    "標籤、仿單及包裝加註": "",
    "藥品類別": "06須由醫師處方使用",
    "主成分略述": [
        "GABAPENTIN"
    ],
    "限制項目": "02輸　入",
    "申請商名稱": "1504401100  輝瑞大藥廠股份有限公司",
    "主製造廠": {
        "主製造廠": "",
        "製造廠名稱": "F370019000  PFIZER PHARMACEUTICALS LLC",
        "製造廠廠址": "KM. 1.9 ROAD 689, VEGA BAJA, PUERTO RICO 00693",
        "製造廠公司地址": "VEGA BAJA,PUERTO RICO,00693",
        "": ""
    },
    "CCC號列": "30049099904 其他醫藥製劑〈不包括第３００２、３００５或３００６節所列者〉包含經混合或未混合產品供治療或預防疾病用，具有劑量（包括經皮給藥形態者）或零售包裝式樣者Other medicaments (excluding goods of heading 30.02, 30.05 or 30.06) consisting of mixed or unmixed products for therapeutic or prophylactic uses,put up in measured doses or in forms or packings for retail sale",
    "藥理治療分類": "",
    "次製造廠": [
        {
            "製造廠名稱": "6605071926  久裕企業股份有限公司",
            "製造廠廠址": "桃園市桃園區大林里興邦路43巷2之1號4樓，3樓B區，1樓A區",
            "製造廠公司地址": "",
            "製造廠國別": "",
            "製程": "二級包裝廠(委託貼標及置入仿單)"
        }
    ],
    "ingredients": [
        {
            "成分類別": "主成分",
            "成分代碼": "2812001700",
            "成分名稱": "GABAPENTIN",
            "含量描述": "",
            "含量": "100.0000000000",
            "單位": "MG"
        }
    ],
    "藥物辨識詳細資料": {
        "外觀尺寸": "",
        "特殊劑型": "",
        "顏色": "白色\/白色",
        "特殊氣味": "",
        "刻痕": "",
        "形狀": "長圓柱形",
        "標記一": "",
        "標記二": "派德4"
    },
    "藥物辨識外觀圖片": [
        {
            "title": "Neurontin 100 mg 外觀-104-09-15(廠商自行上傳).pdf",
            "url": "http:\/\/www.fda.gov.tw\/MLMS\/ShowFile.aspx?LicId=02022823&Seq=436&Type=10"
        }
    ],
    "仿單外盒": [
        {
            "title": "02 022823 0001-106-04-21.pdf",
            "url": "http:\/\/www.fda.gov.tw\/MLMS\/ShowFile.aspx?LicId=02022823&Seq=049&Type=9"
        },
        {
            "title": "Neurontin 100 mg 外盒-104-09-15(廠商自行上傳).pdf",
            "url": "http:\/\/www.fda.gov.tw\/MLMS\/ShowFile.aspx?LicId=02022823&Seq=001&Type=8"
        }
    ]
}