{
    "code": "44007254",
    "url": "https:\/\/www.fda.gov.tw\/MLMS\/H0001D.aspx?Type=Lic&LicId=44007254",
    "time": "2020-02-26 04:57:38",
    "許可證字號": "衛署醫器輸壹字第007254號",
    "註銷狀態": "",
    "註銷日期": "",
    "註銷理由": "",
    "有效日期": "112\/11\/18",
    "發證日期": "97\/11\/18",
    "許可證種類": "醫　器",
    "舊證字號": "",
    "醫療器材級數": "第一等級",
    "通關簽審文件編號": "DHA04400725407",
    "中文品名": "“史密斯”氣管管路固定裝置 (未滅菌)",
    "英文品名": "“Smiths” Tracheal Tube Fixation Holder (Non-sterile)",
    "效能": "限醫療器材管理辦法「氣管管路固定裝置(D.5770)」第一等級鑑別範圍。",
    "醫器規格": "",
    "劑型": "",
    "包裝": "",
    "儲存溫度": "",
    "有效期間": "",
    "指示藥品審查基準": "",
    "標籤、仿單及包裝加註": "",
    "醫器主類別一": "D麻醉學科用裝置",
    "醫器主類別二": [
        ""
    ],
    "醫器主類別三": "",
    "藥品分類": "",
    "主製造廠": {
        "限制項目": "02輸　入",
        "申請商名稱": "1511101100  誼昇有限公司",
        "申請商地址": "台北市建國北路二段８５號４樓",
        "主製造廠": ""
    },
    "藥理治療分類": "",
    "ingredients": []
}