{
    "code": "44002323",
    "url": "https:\/\/info.fda.gov.tw\/MLMS\/H0001D.aspx?Type=Lic&LicId=44002323",
    "time": "2020-09-11 06:46:21",
    "許可證字號": "衛署醫器輸壹字第002323號",
    "註銷狀態": "",
    "註銷日期": "",
    "註銷理由": "",
    "製造許可登錄編號": "",
    "有效日期": "114\/12\/22",
    "發證日期": "94\/12\/22",
    "許可證種類": "醫　器",
    "舊證字號": "",
    "醫療器材級數": "第一等級",
    "通關簽審文件編號": "DHA04400232301",
    "中文品名": "貝爾斯17-皮質類脂醇試劑 (未滅菌)",
    "英文品名": "BioSystems 17-HYDROXYCORTICOSTEROIDS (Non-Sterile)",
    "效能": "測量17-皮質類脂醇濃度用試劑。",
    "醫器規格": "#11006 (40\/TESTS)",
    "劑型": "",
    "包裝": "",
    "儲存溫度": "",
    "有效期間": "",
    "指示藥品審查基準": "",
    "標籤、仿單及包裝加註": "",
    "醫器主類別一": "A臨床化學及臨床毒理學",
    "醫器次類別一": "A138517-皮質類脂醇(17-生酮的類脂醇)試驗系統",
    "醫器主類別二": "",
    "醫器次類別二": "",
    "醫器主類別三": "",
    "醫器次類別三": "",
    "藥品分類": "",
    "監視期限": "",
    "主成分略述": "",
    "限制項目": "02輸　入",
    "申請商名稱": "6231011499  杏友貿易有限公司",
    "申請商地址": "新北市板橋區民生路三段299巷13號4樓",
    "主製造廠": [
        {
            "製造廠名稱": "MES0024000  BIOSYSTEMS",
            "製造廠廠址": "BIOSYSTEMS S.A. COSTA BRAVA. 30. BARCELONA(SPAIN)",
            "製造廠公司地址": "",
            "製造廠國別": "SPAIN",
            "製程": ""
        }
    ],
    "藥理治療分類": "",
    "ingredients": []
}