{
    "code": "08009066",
    "url": "https:\/\/www.fda.gov.tw\/MLMS\/H0001D.aspx?Type=Lic&LicId=08009066",
    "time": "2020-02-25 23:29:13",
    "許可證字號": "衛署粧輸字第009066號",
    "註銷狀態": "已註銷",
    "註銷日期": "98\/12\/23",
    "註銷理由": "未展延而逾期者",
    "有效日期": "97\/02\/14",
    "發證日期": "92\/02\/14",
    "許可證種類": "含藥化粧品",
    "舊證字號": "",
    "醫療器材級數": "",
    "通關簽審文件編號": "DHA00800906602",
    "中文品名": "美絲雅染髮膏－1, 3, 4, 5, 6, 6.1, 8.1",
    "英文品名": "MAJIREL-- 1, 3, 4, 5, 6, 6.1, 8.1",
    "用途": "染髮。",
    "劑型": "992霜劑",
    "包裝": "500ML以下管裝 附外紙盒裝",
    "儲存溫度": "",
    "有效期間": "",
    "指示藥品審查基準": "",
    "標籤、仿單及包裝加註": [
        ""
    ],
    "化粧品類別": "0110染髮劑",
    "藥品分類": "",
    "主製造廠": {
        "限制項目": "02輸　入",
        "申請商名稱": "1428601100  台灣萊雅股份有限公司",
        "申請商地址": "台北市信義區信義路五段7號22樓23樓",
        "主製造廠": ""
    },
    "藥理治療分類": "",
    "ingredients": [
        {
            "成分類別": "主成分",
            "成分代碼": "2820000102",
            "成分名稱": "AMMONIA WATER (AMMONIUM HYDROXIDE)",
            "含量描述": "",
            "含量": "4.4400000000",
            "單位": "%(W\/W)"
        },
        {
            "成分類別": "主成分",
            "成分代碼": "8428000500",
            "成分名稱": "RESORCINOL (RESORCIN)",
            "含量描述": "",
            "含量": "0.5800000000",
            "單位": "%(W\/W)"
        },
        {
            "成分類別": "主成分",
            "成分代碼": "9200035401",
            "成分名稱": "AMINOPHENOL PARA- (EQ TO P-AMINOPHENOL)",
            "含量描述": "",
            "含量": "0.0600000000",
            "單位": "%(W\/W)"
        },
        {
            "成分類別": "主成分",
            "成分代碼": "9200035402",
            "成分名稱": "ORTHO-AMINOPHENOL",
            "含量描述": "",
            "含量": "0.1200000000",
            "單位": "%(W\/W)"
        },
        {
            "成分類別": "主成分",
            "成分代碼": "9200035403",
            "成分名稱": "META-AMINOPHENOL (EQ TO M-AMINOPHENOL)",
            "含量描述": "",
            "含量": "0.1500000000",
            "單位": "%(W\/W)"
        },
        {
            "成分類別": "主成分",
            "成分代碼": "9400003200",
            "成分名稱": "P-PHENYLENEDIAMINE",
            "含量描述": "",
            "含量": "1.8000000000",
            "單位": "%(W\/W)"
        },
        {
            "成分類別": "主成分",
            "成分代碼": "Z102100318",
            "成分名稱": "2,4-DIAMINOPHENOXYETHANOL HCL",
            "含量描述": "",
            "含量": "0.7400000000",
            "單位": "%(W\/W)"
        },
        {
            "成分類別": "主成分",
            "成分代碼": "Z102101349",
            "成分名稱": "HYDROXYBENZOMORPHOLINE",
            "含量描述": "",
            "含量": "0.1200000000",
            "單位": "%(W\/W)"
        },
        {
            "成分類別": "主成分",
            "成分代碼": "2820000102",
            "成分名稱": "AMMONIA WATER (AMMONIUM HYDROXIDE)",
            "含量描述": "",
            "含量": "4.4400000000",
            "單位": "%(W\/W)"
        },
        {
            "成分類別": "主成分",
            "成分代碼": "8428000500",
            "成分名稱": "RESORCINOL (RESORCIN)",
            "含量描述": "",
            "含量": "0.1600000000",
            "單位": "%(W\/W)"
        },
        {
            "成分類別": "主成分",
            "成分代碼": "9200035401",
            "成分名稱": "AMINOPHENOL PARA- (EQ TO P-AMINOPHENOL)",
            "含量描述": "",
            "含量": "0.1000000000",
            "單位": "%(W\/W)"
        },
        {
            "成分類別": "主成分",
            "成分代碼": "9200035402",
            "成分名稱": "ORTHO-AMINOPHENOL",
            "含量描述": "",
            "含量": "0.0700000000",
            "單位": "%(W\/W)"
        },
        {
            "成分類別": "主成分",
            "成分代碼": "9200035403",
            "成分名稱": "META-AMINOPHENOL (EQ TO M-AMINOPHENOL)",
            "含量描述": "",
            "含量": "0.1000000000",
            "單位": "%(W\/W)"
        },
        {
            "成分類別": "主成分",
            "成分代碼": "9400003200",
            "成分名稱": "P-PHENYLENEDIAMINE",
            "含量描述": "",
            "含量": "1.0450000000",
            "單位": "%(W\/W)"
        },
        {
            "成分類別": "主成分",
            "成分代碼": "Z102100318",
            "成分名稱": "2,4-DIAMINOPHENOXYETHANOL HCL",
            "含量描述": "",
            "含量": "0.8600000000",
            "單位": "%(W\/W)"
        },
        {
            "成分類別": "主成分",
            "成分代碼": "Z102101349",
            "成分名稱": "HYDROXYBENZOMORPHOLINE",
            "含量描述": "",
            "含量": "0.0600000000",
            "單位": "%(W\/W)"
        },
        {
            "成分類別": "主成分",
            "成分代碼": "2820000102",
            "成分名稱": "AMMONIA WATER (AMMONIUM HYDROXIDE)",
            "含量描述": "",
            "含量": "4.4400000000",
            "單位": "%(W\/W)"
        },
        {
            "成分類別": "主成分",
            "成分代碼": "8428000500",
            "成分名稱": "RESORCINOL (RESORCIN)",
            "含量描述": "",
            "含量": "0.8480000000",
            "單位": "%(W\/W)"
        },
        {
            "成分類別": "主成分",
            "成分代碼": "9200035401",
            "成分名稱": "AMINOPHENOL PARA- (EQ TO P-AMINOPHENOL)",
            "含量描述": "",
            "含量": "0.1060000000",
            "單位": "%(W\/W)"
        },
        {
            "成分類別": "主成分",
            "成分代碼": "9200035402",
            "成分名稱": "ORTHO-AMINOPHENOL",
            "含量描述": "",
            "含量": "0.1000000000",
            "單位": "%(W\/W)"
        },
        {
            "成分類別": "主成分",
            "成分代碼": "9200035403",
            "成分名稱": "META-AMINOPHENOL (EQ TO M-AMINOPHENOL)",
            "含量描述": "",
            "含量": "0.0480000000",
            "單位": "%(W\/W)"
        },
        {
            "成分類別": "主成分",
            "成分代碼": "9400003200",
            "成分名稱": "P-PHENYLENEDIAMINE",
            "含量描述": "",
            "含量": "0.9540000000",
            "單位": "%(W\/W)"
        },
        {
            "成分類別": "主成分",
            "成分代碼": "Z102100318",
            "成分名稱": "2,4-DIAMINOPHENOXYETHANOL HCL",
            "含量描述": "",
            "含量": "0.0900000000",
            "單位": "%(W\/W)"
        },
        {
            "成分類別": "主成分",
            "成分代碼": "Z102101349",
            "成分名稱": "HYDROXYBENZOMORPHOLINE",
            "含量描述": "",
            "含量": "0.0960000000",
            "單位": "%(W\/W)"
        },
        {
            "成分類別": "主成分",
            "成分代碼": "2820000102",
            "成分名稱": "AMMONIA WATER (AMMONIUM HYDROXIDE)",
            "含量描述": "",
            "含量": "4.4400000000",
            "單位": "%(W\/W)"
        },
        {
            "成分類別": "主成分",
            "成分代碼": "8428000500",
            "成分名稱": "RESORCINOL (RESORCIN)",
            "含量描述": "",
            "含量": "0.6100000000",
            "單位": "%(W\/W)"
        },
        {
            "成分類別": "主成分",
            "成分代碼": "9200035401",
            "成分名稱": "AMINOPHENOL PARA- (EQ TO P-AMINOPHENOL)",
            "含量描述": "",
            "含量": "0.0860000000",
            "單位": "%(W\/W)"
        },
        {
            "成分類別": "主成分",
            "成分代碼": "9200035402",
            "成分名稱": "ORTHO-AMINOPHENOL",
            "含量描述": "",
            "含量": "0.0500000000",
            "單位": "%(W\/W)"
        },
        {
            "成分類別": "主成分",
            "成分代碼": "9200035403",
            "成分名稱": "META-AMINOPHENOL (EQ TO M-AMINOPHENOL)",
            "含量描述": "",
            "含量": "0.0970000000",
            "單位": "%(W\/W)"
        },
        {
            "成分類別": "主成分",
            "成分代碼": "9400003200",
            "成分名稱": "P-PHENYLENEDIAMINE",
            "含量描述": "",
            "含量": "0.5150000000",
            "單位": "%(W\/W)"
        },
        {
            "成分類別": "主成分",
            "成分代碼": "Z102100318",
            "成分名稱": "2,4-DIAMINOPHENOXYETHANOL HCL",
            "含量描述": "",
            "含量": "0.0390000000",
            "單位": "%(W\/W)"
        },
        {
            "成分類別": "主成分",
            "成分代碼": "Z102101349",
            "成分名稱": "HYDROXYBENZOMORPHOLINE",
            "含量描述": "",
            "含量": "0.0170000000",
            "單位": "%(W\/W)"
        },
        {
            "成分類別": "主成分",
            "成分代碼": "2820000102",
            "成分名稱": "AMMONIA WATER (AMMONIUM HYDROXIDE)",
            "含量描述": "",
            "含量": "4.4400000000",
            "單位": "%(W\/W)"
        },
        {
            "成分類別": "主成分",
            "成分代碼": "8428000500",
            "成分名稱": "RESORCINOL (RESORCIN)",
            "含量描述": "",
            "含量": "0.6200000000",
            "單位": "%(W\/W)"
        },
        {
            "成分類別": "主成分",
            "成分代碼": "9200035401",
            "成分名稱": "AMINOPHENOL PARA- (EQ TO P-AMINOPHENOL)",
            "含量描述": "",
            "含量": "0.2650000000",
            "單位": "%(W\/W)"
        },
        {
            "成分類別": "主成分",
            "成分代碼": "9200035402",
            "成分名稱": "ORTHO-AMINOPHENOL",
            "含量描述": "",
            "含量": "0.0400000000",
            "單位": "%(W\/W)"
        },
        {
            "成分類別": "主成分",
            "成分代碼": "9200035403",
            "成分名稱": "META-AMINOPHENOL (EQ TO M-AMINOPHENOL)",
            "含量描述": "",
            "含量": "0.0660000000",
            "單位": "%(W\/W)"
        },
        {
            "成分類別": "主成分",
            "成分代碼": "9400003200",
            "成分名稱": "P-PHENYLENEDIAMINE",
            "含量描述": "",
            "含量": "0.4300000000",
            "單位": "%(W\/W)"
        },
        {
            "成分類別": "主成分",
            "成分代碼": "Z102100318",
            "成分名稱": "2,4-DIAMINOPHENOXYETHANOL HCL",
            "含量描述": "",
            "含量": "0.0330000000",
            "單位": "%(W\/W)"
        },
        {
            "成分類別": "主成分",
            "成分代碼": "Z102101349",
            "成分名稱": "HYDROXYBENZOMORPHOLINE",
            "含量描述": "",
            "含量": "0.0150000000",
            "單位": "%(W\/W)"
        },
        {
            "成分類別": "主成分",
            "成分代碼": "2820000102",
            "成分名稱": "AMMONIA WATER (AMMONIUM HYDROXIDE)",
            "含量描述": "",
            "含量": "4.4400000000",
            "單位": "%(W\/W)"
        },
        {
            "成分類別": "主成分",
            "成分代碼": "8428000500",
            "成分名稱": "RESORCINOL (RESORCIN)",
            "含量描述": "",
            "含量": "0.3000000000",
            "單位": "%(W\/W)"
        },
        {
            "成分類別": "主成分",
            "成分代碼": "9200035401",
            "成分名稱": "AMINOPHENOL PARA- (EQ TO P-AMINOPHENOL)",
            "含量描述": "",
            "含量": "0.0750000000",
            "單位": "%(W\/W)"
        },
        {
            "成分類別": "主成分",
            "成分代碼": "9200035402",
            "成分名稱": "ORTHO-AMINOPHENOL",
            "含量描述": "",
            "含量": "0.0340000000",
            "單位": "%(W\/W)"
        },
        {
            "成分類別": "主成分",
            "成分代碼": "9200035403",
            "成分名稱": "META-AMINOPHENOL (EQ TO M-AMINOPHENOL)",
            "含量描述": "",
            "含量": "0.0650000000",
            "單位": "%(W\/W)"
        },
        {
            "成分類別": "主成分",
            "成分代碼": "9400003200",
            "成分名稱": "P-PHENYLENEDIAMINE",
            "含量描述": "",
            "含量": "0.3480000000",
            "單位": "%(W\/W)"
        },
        {
            "成分類別": "主成分",
            "成分代碼": "Z102100318",
            "成分名稱": "2,4-DIAMINOPHENOXYETHANOL HCL",
            "含量描述": "",
            "含量": "0.0360000000",
            "單位": "%(W\/W)"
        },
        {
            "成分類別": "主成分",
            "成分代碼": "Z102101349",
            "成分名稱": "HYDROXYBENZOMORPHOLINE",
            "含量描述": "",
            "含量": "0.0450000000",
            "單位": "%(W\/W)"
        },
        {
            "成分類別": "主成分",
            "成分代碼": "2820000102",
            "成分名稱": "AMMONIA WATER (AMMONIUM HYDROXIDE)",
            "含量描述": "",
            "含量": "5.1600000000",
            "單位": "%(W\/W)"
        },
        {
            "成分類別": "主成分",
            "成分代碼": "8428000500",
            "成分名稱": "RESORCINOL (RESORCIN)",
            "含量描述": "",
            "含量": "0.1500000000",
            "單位": "%(W\/W)"
        },
        {
            "成分類別": "主成分",
            "成分代碼": "9200035401",
            "成分名稱": "AMINOPHENOL PARA- (EQ TO P-AMINOPHENOL)",
            "含量描述": "",
            "含量": "0.0160000000",
            "單位": "%(W\/W)"
        },
        {
            "成分類別": "主成分",
            "成分代碼": "9200035402",
            "成分名稱": "ORTHO-AMINOPHENOL",
            "含量描述": "",
            "含量": "0.0500000000",
            "單位": "%(W\/W)"
        },
        {
            "成分類別": "主成分",
            "成分代碼": "9200035403",
            "成分名稱": "META-AMINOPHENOL (EQ TO M-AMINOPHENOL)",
            "含量描述": "",
            "含量": "0.0270000000",
            "單位": "%(W\/W)"
        },
        {
            "成分類別": "主成分",
            "成分代碼": "9400003200",
            "成分名稱": "P-PHENYLENEDIAMINE",
            "含量描述": "",
            "含量": "0.1400000000",
            "單位": "%(W\/W)"
        },
        {
            "成分類別": "主成分",
            "成分代碼": "Z102100318",
            "成分名稱": "2,4-DIAMINOPHENOXYETHANOL HCL",
            "含量描述": "",
            "含量": "0.0180000000",
            "單位": "%(W\/W)"
        },
        {
            "成分類別": "主成分",
            "成分代碼": "Z102101349",
            "成分名稱": "HYDROXYBENZOMORPHOLINE",
            "含量描述": "",
            "含量": "0.0260000000",
            "單位": "%(W\/W)"
        }
    ]
}