{
    "code": "08007561",
    "time": "2015-06-23 09:25:12",
    "許可證字號": "衛署粧輸字第007561號",
    "註銷狀態": "已註銷",
    "註銷日期": "101\/11\/09",
    "註銷理由": "許可證已逾有效期",
    "有效日期": "95\/08\/16",
    "發證日期": "90\/08\/16",
    "許可證種類": "含藥化粧品",
    "舊證字號": "",
    "醫療器材級數": "",
    "通關簽審文件編號": "DHA00800756102",
    "中文品名": "柔白防曬乳霜　ＳＰＦ３０",
    "英文品名": "TRANSLUCENT PROTECTIVE EMULSION SPF30",
    "用途": "保護皮膚、防曬。",
    "劑型": "990乳霜劑",
    "包裝": "塑膠管裝 盒裝",
    "化粧品類別": "0714防晒化粧用品",
    "": "",
    "主成分略述": "ZINC OXIDE, TITANIUM DIOXIDE (EQ TO TITANIUM OXIDE), ETHYLHEXYL METHOXYCINNAMATE",
    "限制項目": [
        "02輸入"
    ],
    "申請商名稱": "0938401100  香港商得馨有限公司台灣分公司",
    "申請商地址": "台北市敦化南路一段１８７巷１４號８樓",
    "主製造廠": {
        "製造廠名稱": "C150063000  PARFUMS NINA RICCI",
        "製造廠廠址": "17 RUE FRANCOIS IER 75008 PARIS FRANCE",
        "製造廠公司地址": "",
        "製造廠國別": "FRANCE",
        "製程": ""
    },
    "CCC號列": "33049990108 含藥之乳液、化粧水Medicated lotion, tonic lotion",
    "藥理治療分類": "",
    "ingredients": [
        {
            "成分類別": "主成分",
            "成分代碼": "9200011500",
            "成分名稱": "ZINC OXIDE",
            "含量描述": "9.69",
            "含量": "9.6900000000",
            "單位": "%(W\/W"
        },
        {
            "成分類別": "主成分",
            "成分代碼": "9602020800",
            "成分名稱": "TITANIUM DIOXIDE (EQ TO TITANIUM OXIDE)",
            "含量描述": "3.146",
            "含量": "3.1460000000",
            "單位": "%(W\/W"
        },
        {
            "成分類別": "主成分",
            "成分代碼": "9900071200",
            "成分名稱": "ETHYLHEXYL METHOXYCINNAMATE",
            "含量描述": "7",
            "含量": "7.0000000000",
            "單位": "%(W\/W"
        }
    ]
}