{
    "code": "08010033",
    "url": "https:\/\/info.fda.gov.tw\/MLMS\/H0001D.aspx?Type=Lic&LicId=08010033",
    "time": "2021-03-05 03:58:12",
    "許可證字號": "衛署粧輸字第010033號",
    "註銷狀態": "",
    "註銷日期": "",
    "註銷理由": "",
    "製造許可登錄編號": "",
    "有效日期": "113\/06\/30",
    "發證日期": "93\/02\/03",
    "許可證種類": "特定用途化粧品",
    "舊證字號": "",
    "醫療器材級數": "",
    "通關簽審文件編號": "DHA00801003300",
    "中文品名": "愛麗 希絲 冷燙液",
    "英文品名": "ID CYS A",
    "用途": "冷燙頭髮用。",
    "劑型": "970液劑",
    "包裝": "500ML以下瓶裝",
    "儲存溫度": "",
    "有效期間": "",
    "指示藥品審查基準": "",
    "標籤、仿單及包裝加註": "",
    "化粧品類別": "0111燙髮用劑",
    "": "",
    "藥品分類": "",
    "監視期限": "",
    "主成分略述": "DL-CYSTEINE, SODIUM BROMATE",
    "限制項目": "02輸　入",
    "申請商名稱": "0933301100  美盈有限公司",
    "申請商地址": "台北市延壽街４０２巷３弄２１號１樓",
    "主製造廠": [
        {
            "製造廠名稱": "CJP0166000  MEROS CHEMICAL CO., LTD.",
            "製造廠廠址": "3-7-1, HIGASHII KEBUKURO TOSHIMA-KU, TOKYO JAPAN",
            "製造廠公司地址": "",
            "製造廠國別": "JAPAN",
            "製程": ""
        }
    ],
    "藥理治療分類": "",
    "ingredients": [
        {
            "成分類別": "主成分",
            "成分代碼": "4020100515",
            "成分名稱": "DL-CYSTEINE",
            "含量描述": "(3-7.5%)",
            "含量": "",
            "單位": "%(W\/V)"
        },
        {
            "成分類別": "主成分",
            "成分代碼": "9400003410",
            "成分名稱": "SODIUM BROMATE",
            "含量描述": "(NOT MORE THAN)",
            "含量": "11.5000000000",
            "單位": "%(W\/V)"
        }
    ],
    "仿單外盒": [
        {
            "title": "08010033-105-09-19.pdf",
            "url": "https:\/\/www.fda.gov.tw\/MLMS\/ShowFile.aspx?LicId=08010033&Seq=001&Type=8"
        }
    ]
}