{
    "code": "06004490",
    "url": "https:\/\/info.fda.gov.tw\/MLMS\/H0001D.aspx?Type=Lic&LicId=06004490",
    "time": "2020-02-25 16:35:35",
    "許可證字號": "衛署醫器輸字第004490號",
    "註銷狀態": "已註銷",
    "註銷日期": "93\/10\/27",
    "註銷理由": "未展延而逾期者",
    "製造許可登錄編號": "",
    "有效日期": "80\/12\/18",
    "發證日期": "75\/12\/18",
    "許可證種類": "醫　器",
    "舊證字號": "",
    "醫療器材級數": "",
    "通關簽審文件編號": "DHA00600449000",
    "中文品名": "露比安衛生套",
    "英文品名": "&quot;SAGAMI&quot; LUBIAN CONDOM",
    "效能": "",
    "醫器規格": "ＣＯＬＯＲ：　　　　　　　　　　　　　　　　　　　　　　　　　　　　ＶＩＯＬＥＴ，　ＯＰＡＬ，　ＮＡＴＵＲＥ",
    "劑型": "",
    "包裝": "",
    "儲存溫度": "",
    "有效期間": "",
    "指示藥品審查基準": "",
    "標籤、仿單及包裝加註": "",
    "醫器主類別一": "2701衛生套",
    "醫器次類別一": "",
    "醫器主類別二": "",
    "醫器次類別二": "",
    "醫器主類別三": "",
    "醫器次類別三": "",
    "藥品分類": "",
    "監視期限": "",
    "主成分略述": "",
    "限制項目": "02輸　入",
    "申請商名稱": "1424101100  臺灣雅客股份有限公司",
    "申請商地址": "台北巿仁愛路四段３４５巷５弄９號地下室",
    "主製造廠": [
        {
            "製造廠名稱": "MJP0186000  SAGAMI RUBBER INDUSTRIES CO. LTD.",
            "製造廠廠址": "2-1 MOTO-CHO ATSUGISHI KANAGAWA-KEN JAPAN.",
            "製造廠公司地址": "",
            "製造廠國別": "JAPAN",
            "製程": ""
        }
    ],
    "藥理治療分類": "",
    "ingredients": []
}