{
    "code": "06016333",
    "url": "http:\/\/www.fda.gov.tw\/MLMS\/H0001D.aspx?Type=Lic&LicId=06016333",
    "time": "2016-01-08 04:57:50",
    "許可證字號": "衛署醫器輸字第016333號",
    "註銷狀態": "",
    "註銷日期": "",
    "註銷理由": "",
    "有效日期": "110\/04\/11",
    "發證日期": "95\/04\/11",
    "許可證種類": "醫　器",
    "舊證字號": "",
    "醫療器材級數": "第二等級",
    "通關簽審文件編號": "DHA00601633300",
    "中文品名": "0.8% 利薩夫紅血球試劑套組",
    "英文品名": "Reagent Red Blood Cells 0.8% Resolve Panel",
    "效能": "鑑定血液中未知抗體之定性試驗。",
    "醫器規格": "Panel A: 11 x 3 mlPanel B: 11 x 3 mlPanel C System: 22 x 3ml",
    "劑型": "",
    "包裝": "",
    "醫器主類別一": "B血液學及病理學裝置",
    "醫器次類別一": "B9650血庫作業反應劑之品管器材",
    "醫器主類別二": "",
    "醫器次類別二": "",
    "醫器主類別三": "",
    "醫器次類別三": "",
    "主成分略述": "",
    "限制項目": [
        "02輸入"
    ],
    "申請商名稱": "620118D857  台灣大昌華嘉股份有限公司",
    "申請商地址": "台北市內湖區堤頂大道二段407巷20弄1、3、5、7號10樓及22、24、26號10樓及22號10樓之1",
    "主製造廠": {
        "製造廠名稱": "M462652000  ORTHO-CLINICAL DIAGNOSTICS, INC.",
        "製造廠廠址": "1001 U.S. HIGHWAY 202, RARITAN, NEW JERSEY 08869 U.S.A.",
        "製造廠公司地址": "",
        "製造廠國別": "UNITED STATES",
        "製程": ""
    },
    "CCC號列": "30062000004 血型分類試藥Blood-grouping reagents",
    "藥理治療分類": "",
    "ingredients": [],
    "仿單外盒": [
        {
            "title": "060163330004.jpg",
            "url": "http:\/\/www.fda.gov.tw\/MLMS\/ShowFile.aspx?LicId=06016333&Seq=004&Type=9"
        },
        {
            "title": "060163330003.jpg",
            "url": "http:\/\/www.fda.gov.tw\/MLMS\/ShowFile.aspx?LicId=06016333&Seq=003&Type=9"
        },
        {
            "title": "060163330002.jpg",
            "url": "http:\/\/www.fda.gov.tw\/MLMS\/ShowFile.aspx?LicId=06016333&Seq=002&Type=9"
        },
        {
            "title": "060163330001.jpg",
            "url": "http:\/\/www.fda.gov.tw\/MLMS\/ShowFile.aspx?LicId=06016333&Seq=001&Type=9"
        },
        {
            "title": "060163330003.jpg",
            "url": "http:\/\/www.fda.gov.tw\/MLMS\/ShowFile.aspx?LicId=06016333&Seq=003&Type=8"
        },
        {
            "title": "060163330002.jpg",
            "url": "http:\/\/www.fda.gov.tw\/MLMS\/ShowFile.aspx?LicId=06016333&Seq=002&Type=8"
        },
        {
            "title": "060163330001.jpg",
            "url": "http:\/\/www.fda.gov.tw\/MLMS\/ShowFile.aspx?LicId=06016333&Seq=001&Type=8"
        }
    ]
}