{
    "code": "06020620",
    "url": "https:\/\/info.fda.gov.tw\/MLMS\/H0001D.aspx?Type=Lic&LicId=06020620",
    "time": "2020-04-24 04:42:41",
    "許可證字號": "衛署醫器輸字第020620號",
    "註銷狀態": "",
    "註銷日期": "",
    "註銷理由": "",
    "製造許可登錄編號": "QSD4970",
    "有效日期": "109\/03\/02",
    "發證日期": "99\/03\/02",
    "許可證種類": "醫　器",
    "舊證字號": "",
    "醫療器材級數": "第二等級",
    "通關簽審文件編號": "DHA00602062002",
    "中文品名": "“聖猷達”壓力感應金屬導引線",
    "英文品名": "“SJM” Pressure Wire Certus",
    "效能": "詳如中文仿單核定本",
    "醫器規格": "12006以下空白",
    "劑型": "",
    "包裝": "",
    "儲存溫度": "",
    "有效期間": "",
    "指示藥品審查基準": "",
    "標籤、仿單及包裝加註": "",
    "醫器主類別一": "E心臟血管用裝置",
    "醫器次類別一": "E2870導管尖端壓力傳導器",
    "醫器主類別二": "",
    "醫器次類別二": "",
    "醫器主類別三": "",
    "醫器次類別三": "",
    "藥品分類": "",
    "監視期限": "",
    "主成分略述": "",
    "限制項目": "02輸　入",
    "申請商名稱": "6201118547  台灣聖猷達醫療用品有限公司",
    "申請商地址": "台北市內湖區瑞光路407號5樓",
    "主製造廠": [
        {
            "製造廠名稱": "MSE0825000  ST. JUDE MEDICAL SYSTEMS AB",
            "製造廠廠址": "PALMBLADSGATAN 10, BOX 6350, SE-751 35 UPPSALA, SWEDEN",
            "製造廠公司地址": "",
            "製造廠國別": "SWEDEN",
            "製程": ""
        }
    ],
    "藥理治療分類": "",
    "ingredients": [],
    "仿單外盒": [
        {
            "title": "060206200020.pdf",
            "url": "https:\/\/www.fda.gov.tw\/MLMS\/ShowFile.aspx?LicId=06020620&Seq=019&Type=9"
        },
        {
            "title": "060206200019.pdf",
            "url": "https:\/\/www.fda.gov.tw\/MLMS\/ShowFile.aspx?LicId=06020620&Seq=018&Type=9"
        },
        {
            "title": "060206200018.pdf",
            "url": "https:\/\/www.fda.gov.tw\/MLMS\/ShowFile.aspx?LicId=06020620&Seq=017&Type=9"
        },
        {
            "title": "060206200017.pdf",
            "url": "https:\/\/www.fda.gov.tw\/MLMS\/ShowFile.aspx?LicId=06020620&Seq=016&Type=9"
        },
        {
            "title": "060206200016.pdf",
            "url": "https:\/\/www.fda.gov.tw\/MLMS\/ShowFile.aspx?LicId=06020620&Seq=015&Type=9"
        },
        {
            "title": "060206200015.pdf",
            "url": "https:\/\/www.fda.gov.tw\/MLMS\/ShowFile.aspx?LicId=06020620&Seq=014&Type=9"
        },
        {
            "title": "060206200014.pdf",
            "url": "https:\/\/www.fda.gov.tw\/MLMS\/ShowFile.aspx?LicId=06020620&Seq=013&Type=9"
        },
        {
            "title": "060206200013.pdf",
            "url": "https:\/\/www.fda.gov.tw\/MLMS\/ShowFile.aspx?LicId=06020620&Seq=012&Type=9"
        },
        {
            "title": "060206200012.pdf",
            "url": "https:\/\/www.fda.gov.tw\/MLMS\/ShowFile.aspx?LicId=06020620&Seq=011&Type=9"
        },
        {
            "title": "060206200011.pdf",
            "url": "https:\/\/www.fda.gov.tw\/MLMS\/ShowFile.aspx?LicId=06020620&Seq=010&Type=9"
        },
        {
            "title": "060206200010.pdf",
            "url": "https:\/\/www.fda.gov.tw\/MLMS\/ShowFile.aspx?LicId=06020620&Seq=009&Type=9"
        },
        {
            "title": "060206200009.pdf",
            "url": "https:\/\/www.fda.gov.tw\/MLMS\/ShowFile.aspx?LicId=06020620&Seq=008&Type=9"
        },
        {
            "title": "060206200008.pdf",
            "url": "https:\/\/www.fda.gov.tw\/MLMS\/ShowFile.aspx?LicId=06020620&Seq=007&Type=9"
        },
        {
            "title": "060206200007.pdf",
            "url": "https:\/\/www.fda.gov.tw\/MLMS\/ShowFile.aspx?LicId=06020620&Seq=006&Type=9"
        },
        {
            "title": "060206200006.pdf",
            "url": "https:\/\/www.fda.gov.tw\/MLMS\/ShowFile.aspx?LicId=06020620&Seq=005&Type=9"
        },
        {
            "title": "060206200005.pdf",
            "url": "https:\/\/www.fda.gov.tw\/MLMS\/ShowFile.aspx?LicId=06020620&Seq=004&Type=9"
        },
        {
            "title": "060206200004.pdf",
            "url": "https:\/\/www.fda.gov.tw\/MLMS\/ShowFile.aspx?LicId=06020620&Seq=003&Type=9"
        },
        {
            "title": "060206200003.pdf",
            "url": "https:\/\/www.fda.gov.tw\/MLMS\/ShowFile.aspx?LicId=06020620&Seq=002&Type=9"
        },
        {
            "title": "060206200002.pdf",
            "url": "https:\/\/www.fda.gov.tw\/MLMS\/ShowFile.aspx?LicId=06020620&Seq=001&Type=9"
        },
        {
            "title": "060206200001.pdf",
            "url": "https:\/\/www.fda.gov.tw\/MLMS\/ShowFile.aspx?LicId=06020620&Seq=001&Type=8"
        }
    ]
}