{
    "code": "10000375",
    "url": "https:\/\/info.fda.gov.tw\/MLMS\/H0001D.aspx?Type=Lic&LicId=10000375",
    "time": "2020-02-26 01:36:37",
    "許可證字號": "衛署菌疫輸字第000375號",
    "註銷狀態": "",
    "註銷日期": "",
    "註銷理由": "",
    "製造許可登錄編號": "",
    "有效日期": "113\/09\/11",
    "發證日期": "103\/07\/04",
    "許可證種類": "菌　疫",
    "舊證字號": "10000111",
    "醫療器材級數": "",
    "通關簽審文件編號": "DHA01000037503",
    "中文品名": "艾爾補定注射液２５％",
    "英文品名": "ALBUTEIN 25% SOLUTION",
    "適應症": "低蛋白血症、休克、燒傷。",
    "劑型": "270注射劑",
    "包裝": "50、100毫升瓶裝",
    "儲存溫度": "",
    "有效期間": "",
    "指示藥品審查基準": "",
    "標籤、仿單及包裝加註": "",
    "藥品類別": "05限由醫師使用",
    "管制藥品分類級別": "",
    "藥品分類": "血液衍生產品",
    "監視期限": "",
    "主成分略述": "ALBUMIN HUMAN SERUM",
    "限制項目": "02輸　入",
    "申請商名稱": "1409720100  台灣綠十字股份有限公司",
    "申請商地址": "台北市大同區承德路三段二四四號六樓",
    "主製造廠": [
        {
            "製造廠名稱": "FUS0014000  Grifols Biologicals LLC",
            "製造廠廠址": "5555 VALLEY BOULEVARD, LOS ANGELES, CALIFORNIA 90032",
            "製造廠公司地址": "",
            "製造廠國別": "UNITED STATES",
            "製程": ""
        }
    ],
    "次製造廠": [
        {
            "製造廠名稱": "FES0117000  INSTITUTO GRIFOLS S.A.",
            "製造廠廠址": "POLIGONO LEVANTE C\/CAN GUASCH 2, 08150 PARETS DEL VALLES BARCELONA SPAIN",
            "製造廠公司地址": "",
            "製造廠國別": "SPAIN",
            "製程": "FRACTION V"
        },
        {
            "製造廠名稱": "FUS0255000  Grifols Therapeutics LLC",
            "製造廠廠址": "8368 US 70 BUS HWY WEST, CLAYTON, NC 27520, U.S.A.",
            "製造廠公司地址": "RESEARCH TRIANGLE PARK, 79 T.W.ALEXANDER DRIVE, NORTH CAROLINA, 27709, U.S.A.",
            "製造廠國別": "UNITED STATES",
            "製程": "FRACTION V"
        },
        {
            "製造廠名稱": "FUS0635000  GRIFOLS BIOLOGICALS LLC",
            "製造廠廠址": "13111 TEMPLE AVENUE, CITY OF INDUSTRY, CA 91746, USA",
            "製造廠公司地址": "",
            "製造廠國別": "UNITED STATES",
            "製程": "包裝"
        }
    ],
    "CCC號列": "",
    "藥理治療分類": "",
    "ingredients": [
        {
            "成分類別": "主成分",
            "成分代碼": "8004000211",
            "成分名稱": "ALBUMIN HUMAN SERUM",
            "含量描述": "",
            "含量": "0.2500000000",
            "單位": "GM"
        }
    ],
    "藥物辨識詳細資料": {
        "外觀尺寸": "",
        "特殊劑型": "",
        "顏色": "",
        "特殊氣味": "",
        "刻痕": "",
        "形狀": "",
        "標記一": "",
        "標記二": ""
    },
    "藥物辨識外觀圖片": [
        {
            "title": "Albutein 25% 外觀照片-104-09-08(廠商自行上傳).pdf",
            "url": "https:\/\/www.fda.gov.tw\/MLMS\/ShowFile.aspx?LicId=10000375&Seq=001&Type=10"
        }
    ],
    "仿單外盒": [
        {
            "title": "Albutein25- 衛署菌疫輸字第000375號-107-03-26.pdf",
            "url": "https:\/\/www.fda.gov.tw\/MLMS\/ShowFile.aspx?LicId=10000375&Seq=011&Type=9"
        },
        {
            "title": "100003750011.pdf",
            "url": "https:\/\/www.fda.gov.tw\/MLMS\/ShowFile.aspx?LicId=10000375&Seq=011&Type=8"
        }
    ]
}