{
    "code": "07003169",
    "url": "http:\/\/www.fda.gov.tw\/MLMS\/H0001D.aspx?Type=Lic&LicId=07003169",
    "time": "2016-11-19 02:20:59",
    "許可證字號": "衛署粧製字第003169號",
    "註銷狀態": "已註銷",
    "註銷日期": "98\/12\/22",
    "註銷理由": "未展延而逾期者",
    "有效日期": "96\/09\/11",
    "發證日期": "91\/09\/11",
    "許可證種類": "含藥化粧品",
    "舊證字號": "",
    "醫療器材級數": "",
    "通關簽審文件編號": "DHY00700316901",
    "中文品名": "全球詩葳特生桂防曬美白霜",
    "英文品名": "&quot;SWITER&quot; BEAUTY CREAM",
    "用途": "防曬、美白肌膚、預防黑斑、雀斑之形成。",
    "劑型": "944乳劑",
    "包裝": "500GM以下玻璃瓶裝",
    "標籤、仿單及包裝加註": "",
    "化粧品類別": "0708防晒面霜",
    "主成分略述": [
        "ARBUTIN,OCTYLMETHOXYCINNAMATE(PARSOLKCX)"
    ],
    "限制項目": "01國　產",
    "申請商名稱": "1237022200  雲釆瀲艷企業有限公司",
    "主製造廠": {
        "主製造廠": "",
        "製造廠名稱": "1237022500  雲釆瀲艷企業有限公司",
        "製造廠廠址": "高雄縣燕巢鄉安林路１８號",
        "製造廠公司地址": "",
        "": ""
    },
    "CCC號列": "",
    "藥理治療分類": "",
    "ingredients": [
        {
            "成分類別": "主成分",
            "成分代碼": "0836000100",
            "成分名稱": "ARBUTIN",
            "含量描述": "",
            "含量": "5.0000000000",
            "單位": "%(W\/W)"
        },
        {
            "成分類別": "主成分",
            "成分代碼": "8480000520",
            "成分名稱": "OCTYL METHOXYCINNAMATE (PARSOL KCX)",
            "含量描述": "",
            "含量": "3.0000000000",
            "單位": "%(W\/W)"
        }
    ]
}