{
    "code": "07005003",
    "time": "2015-06-23 01:28:22",
    "許可證字號": "衛署粧製字第005003號",
    "註銷狀態": "",
    "註銷日期": "",
    "註銷理由": "",
    "有效日期": "107\/04\/07",
    "發證日期": "98\/04\/07",
    "許可證種類": "含藥化粧品",
    "舊證字號": "",
    "醫療器材級數": "",
    "通關簽審文件編號": "DHY00700500303",
    "中文品名": "輕透美白身體防曬乳",
    "英文品名": "SUN SHADES WHITENING SUNSCREEN, SPF30 ★★",
    "用途": "防曬、隔離紫外線、美白、保濕。",
    "劑型": "944乳劑",
    "包裝": "500公克以下軟管裝 附外盒裝 10公克鋁箔包裝",
    "化粧品類別": "0714防晒化粧用品",
    "": "",
    "主成分略述": "2-ETHYLHEXYL-4-METHOXY-CINNAMATE, OCTOCRYLENE",
    "限制項目": [
        "01國產"
    ],
    "申請商名稱": "0937701100  美商亞洲美樂家有限公司台灣分公司",
    "申請商地址": "台北市松山區八德路四段760號3樓",
    "主製造廠": {
        "製造廠名稱": "0502110500  永信藥品工業股份有限公司",
        "製造廠廠址": "台中市大甲區中山路一段1191號",
        "製造廠公司地址": "",
        "製造廠國別": "TAIWAN",
        "製程": ""
    },
    "CCC號列": "",
    "藥理治療分類": "",
    "ingredients": [
        {
            "成分類別": "主成分",
            "成分代碼": "8480000510",
            "成分名稱": "2-ETHYLHEXYL-4-METHOXY-CINNAMATE",
            "含量描述": "",
            "含量": "4.0000000000",
            "單位": "%(W\/W)"
        },
        {
            "成分類別": "主成分",
            "成分代碼": "9900066000",
            "成分名稱": "OCTOCRYLENE",
            "含量描述": "",
            "含量": "2.0000000000",
            "單位": "%(W\/W)"
        }
    ],
    "仿單外盒": [
        {
            "title": "外盒 07005003___20120425.pdf 070050030004.jpg 070050030003.jpg 070050030002.jpg 070050030001.jpg",
            "url": "http:\/\/www.fda.gov.tw\/MLMS\/ShowFile.aspx?LicId=07005003&Seq=005&Type=8"
        }
    ]
}