{
    "code": "07006367",
    "time": "2015-06-23 03:40:19",
    "許可證字號": "衛署粧製字第006367號",
    "註銷狀態": "",
    "註銷日期": "",
    "註銷理由": "",
    "有效日期": "106\/11\/09",
    "發證日期": "101\/11\/09",
    "許可證種類": "含藥化粧品",
    "舊證字號": "",
    "醫療器材級數": "",
    "通關簽審文件編號": "",
    "中文品名": "美白淡斑修護霜、晶透靚白霜、極致美白菁華霜",
    "英文品名": "Whitening Repair Cream, Crystal Whitening Cream, Ultimate Whitening Cream",
    "用途": "抑制黑色素形成。",
    "劑型": "992霜劑",
    "包裝": "500毫克以下瓶裝附外盒",
    "化粧品類別": "1701美白化粧用品",
    "": "",
    "主成分略述": "ASCORBYL TETRAISOPALMITATE",
    "限制項目": [
        "01國產"
    ],
    "申請商名稱": "0810410200  佳妙國際股份有限公司",
    "申請商地址": "台中市大里區中興路二段56之1號",
    "主製造廠": {
        "製造廠名稱": "0810410200  佳妙國際股份有限公司",
        "製造廠廠址": "台中市大里區中興路二段56之1號",
        "製造廠公司地址": "",
        "製造廠國別": "TAIWAN",
        "製程": ""
    },
    "CCC號列": "",
    "藥理治療分類": "",
    "ingredients": [
        {
            "成分類別": "主成分",
            "成分代碼": "8816000360",
            "成分名稱": "ASCORBYL TETRAISOPALMITATE",
            "含量描述": "",
            "含量": "3.0000000000",
            "單位": "%(W\/W)"
        }
    ],
    "仿單外盒": [
        {
            "title": "外盒 07006367___20121205.pdf",
            "url": "http:\/\/www.fda.gov.tw\/MLMS\/ShowFile.aspx?LicId=07006367&Seq=001&Type=8"
        }
    ]
}